Metadata-Version: 1.1
Name: collective.spaces
Version: 1.1
Summary: Simple collaboration spaces for Plone
Home-page: http://github.com/collective/collective.spaces
Author: JCU eResearch Centre
Author-email: eresearch@jcu.edu.au
License: gpl
Keywords: plone site space mini-site navigationroot
Platform: UNKNOWN
Classifier: Programming Language :: Python
